sooj1n_lotto/__init__.py
sooj1n_lotto/draw.py
sooj1n_lotto-0.2.0.dist-info/METADATA
sooj1n_lotto-0.2.0.dist-info/WHEEL
sooj1n_lotto-0.2.0.dist-info/top_level.txt
sooj1n_lotto-0.2.0.dist-info/RECORD
