Metadata-Version: 2.1
Name: sooj1n_lotto
Version: 0.2.0
Summary: Default template for PDM package
Author-email: sooj1n <sujin19371@gmail.com>
License: MIT
Requires-Python: >=3.9
